rising_plugin/__init__.py
rising_plugin/csv_embed.py
rising_plugin/image_embedding.py
rising_plugin/pinecone_engine.py
rising_plugin/risingplugin.py
rising_plugin/common/__init__.py
rising_plugin/common/utils.py
rising_plugin/guardrails-config/__init__.py
rising_plugin/guardrails-config/config.yml
rising_plugin/guardrails-config/general.co
rising_plugin/guardrails-config/off-security.co
rising_plugin/guardrails-config/actions/__init__.py
rising_plugin/guardrails-config/actions/actions.py
rising_plugin/guardrails-config/actions/phone.csv
rising_plugin/guardrails-config/actions/phone.json
rising_plugin-0.1.10.dist-info/METADATA
rising_plugin-0.1.10.dist-info/WHEEL
rising_plugin-0.1.10.dist-info/licenses/LICENSE
rising_plugin-0.1.10.dist-info/RECORD
